pytest_taskgraph/__init__.py
pytest_taskgraph/fixtures/gen.py
pytest_taskgraph/fixtures/vcs.py
pytest_taskgraph-0.2.0.dist-info/METADATA
pytest_taskgraph-0.2.0.dist-info/WHEEL
pytest_taskgraph-0.2.0.dist-info/entry_points.txt
pytest_taskgraph-0.2.0.dist-info/RECORD
